sports_betting_module/__init__.py
sports_betting_module/sports_betting_scorer.py
sports_betting_scorer-0.0.3.dist-info/LICENSE
sports_betting_scorer-0.0.3.dist-info/METADATA
sports_betting_scorer-0.0.3.dist-info/WHEEL
sports_betting_scorer-0.0.3.dist-info/top_level.txt
sports_betting_scorer-0.0.3.dist-info/RECORD
